telemetryflow/__init__.py
telemetryflow/banner.py
telemetryflow/builder.py
telemetryflow/client.py
telemetryflow/py.typed
telemetryflow/version.py
telemetryflow/application/__init__.py
telemetryflow/application/commands.py
telemetryflow/application/queries.py
telemetryflow/cli/__init__.py
telemetryflow/cli/generator.py
telemetryflow/cli/generator_restapi.py
telemetryflow/cli/templates/__init__.py
telemetryflow/cli/templates/native/README.md.tpl
telemetryflow/cli/templates/native/__init__.py
telemetryflow/cli/templates/native/env.tpl
telemetryflow/cli/templates/native/example_basic.py.tpl
telemetryflow/cli/templates/native/example_grpc_server.py.tpl
telemetryflow/cli/templates/native/example_http_server.py.tpl
telemetryflow/cli/templates/native/example_worker.py.tpl
telemetryflow/cli/templates/native/init.py.tpl
telemetryflow/cli/templates/native/logs.py.tpl
telemetryflow/cli/templates/native/metrics.py.tpl
telemetryflow/cli/templates/native/traces.py.tpl
telemetryflow/cli/templates/restapi/__init__.py
telemetryflow/cli/templates/restapi/application/__init__.py
telemetryflow/cli/templates/restapi/application/base_command.py.tpl
telemetryflow/cli/templates/restapi/application/base_dto.py.tpl
telemetryflow/cli/templates/restapi/application/base_handler.py.tpl
telemetryflow/cli/templates/restapi/application/base_query.py.tpl
telemetryflow/cli/templates/restapi/docs/API.md.tpl
telemetryflow/cli/templates/restapi/docs/ARCHITECTURE.md.tpl
telemetryflow/cli/templates/restapi/docs/DEPLOYMENT.md.tpl
telemetryflow/cli/templates/restapi/docs/DEVELOPMENT.md.tpl
telemetryflow/cli/templates/restapi/docs/__init__.py
telemetryflow/cli/templates/restapi/domain/__init__.py
telemetryflow/cli/templates/restapi/domain/base_entity.py.tpl
telemetryflow/cli/templates/restapi/domain/base_repository.py.tpl
telemetryflow/cli/templates/restapi/entity/__init__.py
telemetryflow/cli/templates/restapi/entity/command_handler.py.tpl
telemetryflow/cli/templates/restapi/entity/commands.py.tpl
telemetryflow_python_sdk-1.1.2.dist-info/licenses/LICENSE
telemetryflow_python_sdk-1.1.2.dist-info/METADATA
telemetryflow_python_sdk-1.1.2.dist-info/WHEEL
telemetryflow_python_sdk-1.1.2.dist-info/entry_points.txt
telemetryflow_python_sdk-1.1.2.dist-info/top_level.txt
telemetryflow_python_sdk-1.1.2.dist-info/RECORD
