Metadata-Version: 2.4
Name: telemetryflow-python-sdk
Version: 1.1.2
Summary: TelemetryFlow Python SDK - OpenTelemetry-based observability SDK for metrics, logs, and traces
Author-email: TelemetryFlow <support@telemetryflow.id>
Maintainer-email: TelemetryFlow <support@telemetryflow.id>
License: Apache-2.0
Project-URL: Homepage, https://telemetryflow.id
Project-URL: Documentation, https://docs.telemetryflow.id
Project-URL: Repository, https://github.com/telemetryflow/telemetryflow-python-sdk
Project-URL: Issues, https://github.com/telemetryflow/telemetryflow-python-sdk/issues
Project-URL: Changelog, https://github.com/telemetryflow/telemetryflow-python-sdk/blob/main/CHANGELOG.md
Keywords: telemetry,observability,opentelemetry,otel,metrics,logs,traces,monitoring,apm,telemetryflow
Classifier: Development Status :: 5 - Production/Stable
Classifier: Intended Audience :: Developers
Classifier: License :: OSI Approved :: Apache Software License
Classifier: Operating System :: OS Independent
Classifier: Programming Language :: Python :: 3
Classifier: Programming Language :: Python :: 3.12
Classifier: Programming Language :: Python :: 3.13
Classifier: Topic :: System :: Monitoring
Classifier: Topic :: Software Development :: Libraries :: Python Modules
Classifier: Typing :: Typed
Requires-Python: >=3.12
License-File: LICENSE
Requires-Dist: opentelemetry-api>=1.28.0
Requires-Dist: opentelemetry-sdk>=1.28.0
Requires-Dist: opentelemetry-exporter-otlp-proto-grpc>=1.28.0
Requires-Dist: opentelemetry-exporter-otlp-proto-http>=1.28.0
Requires-Dist: opentelemetry-semantic-conventions>=0.49b0
Provides-Extra: dev
Requires-Dist: pytest>=8.0.0; extra == "dev"
Requires-Dist: pytest-asyncio>=0.24.0; extra == "dev"
Requires-Dist: pytest-cov>=5.0.0; extra == "dev"
Requires-Dist: mypy>=1.11.0; extra == "dev"
Requires-Dist: ruff>=0.6.0; extra == "dev"
Requires-Dist: black>=24.0.0; extra == "dev"
Requires-Dist: isort>=5.13.0; extra == "dev"
Requires-Dist: pre-commit>=3.8.0; extra == "dev"
Requires-Dist: build>=1.0.0; extra == "dev"
Provides-Extra: http
Requires-Dist: flask>=3.0.0; extra == "http"
Requires-Dist: fastapi>=0.115.0; extra == "http"
Requires-Dist: starlette>=0.41.0; extra == "http"
Provides-Extra: grpc
Requires-Dist: grpcio>=1.68.0; extra == "grpc"
Provides-Extra: restapi
Requires-Dist: flask>=3.0.0; extra == "restapi"
Requires-Dist: flask-cors>=4.0.0; extra == "restapi"
Requires-Dist: flask-limiter>=3.5.0; extra == "restapi"
Requires-Dist: flask-jwt-extended>=4.6.0; extra == "restapi"
Requires-Dist: flask-sqlalchemy>=3.1.0; extra == "restapi"
Requires-Dist: flasgger>=0.9.7; extra == "restapi"
Requires-Dist: sqlalchemy>=2.0.0; extra == "restapi"
Requires-Dist: alembic>=1.13.0; extra == "restapi"
Requires-Dist: pydantic>=2.5.0; extra == "restapi"
Requires-Dist: python-dotenv>=1.0.0; extra == "restapi"
Provides-Extra: instrumentation
Requires-Dist: opentelemetry-instrumentation>=0.49b0; extra == "instrumentation"
Requires-Dist: opentelemetry-instrumentation-flask>=0.49b0; extra == "instrumentation"
Requires-Dist: opentelemetry-instrumentation-fastapi>=0.49b0; extra == "instrumentation"
Requires-Dist: opentelemetry-instrumentation-sqlalchemy>=0.49b0; extra == "instrumentation"
Requires-Dist: opentelemetry-instrumentation-requests>=0.49b0; extra == "instrumentation"
Requires-Dist: opentelemetry-instrumentation-httpx>=0.49b0; extra == "instrumentation"
Requires-Dist: opentelemetry-instrumentation-logging>=0.49b0; extra == "instrumentation"
Requires-Dist: opentelemetry-instrumentation-psycopg2>=0.49b0; extra == "instrumentation"
Requires-Dist: opentelemetry-instrumentation-redis>=0.49b0; extra == "instrumentation"
Provides-Extra: all
Requires-Dist: telemetryflow-python-sdk[grpc,http,instrumentation,restapi]; extra == "all"
Dynamic: license-file
